Metadata-Version: 2.1
Name: colin-qinglong
Version: 1.0.3
Summary: 个人使用
Home-page: https://github.com/LiuYang7/MyqinglongSDK
Author: colin
Author-email: colin@163.com
License-File: LICENSE.txt
